djgql/__init__.py
djgql/auth/__init__.py
djgql/auth/decorator.py
djgql/auth/middleware.py
djgql/exceptions.py
djgql/response.py
djgql/settings.py
djgql/views.py
django_gql-0.0.1.dist-info/WHEEL
django_gql-0.0.1.dist-info/METADATA
django_gql-0.0.1.dist-info/RECORD
