Metadata-Version: 2.1
Name: django-gql
Version: 0.0.1
Summary: 
Home-page: https://github.com/syfun/django-graphql
License: MIT
Author: syfun
Author-email: sunyu418@gmail.com
Requires-Python: >=3.7
Classifier: License :: OSI Approved :: MIT License
Classifier: Programming Language :: Python :: 3
Classifier: Programming Language :: Python :: 3.7
Classifier: Programming Language :: Python :: 3.8
Requires-Dist: django (>=3,<4)
Requires-Dist: python-gql (<0.1)
